setup.py
protoc/__init__.py
protoc/protoc.py
protoc.egg-info/PKG-INFO
protoc.egg-info/SOURCES.txt
protoc.egg-info/dependency_links.txt
protoc.egg-info/top_level.txt