Metadata-Version: 2.1
Name: protoc
Version: 0.0.1
Summary: Protocol function support- mainly used in bot dev, etc.
Author: q_q
